README.md
license.txt
setup.py
my_package_xy/__init__.py
my_package_xy/__main__.py
my_package_xy/workshops.py
my_package_xy.egg-info/PKG-INFO
my_package_xy.egg-info/SOURCES.txt
my_package_xy.egg-info/dependency_links.txt
my_package_xy.egg-info/requires.txt
my_package_xy.egg-info/top_level.txt