Metadata-Version: 2.1
Name: my-package-xy
Version: 0.0.1
Summary: This package allows getting the API from CodigoFacilito
Home-page: UNKNOWN
Author: Ximena Yeraldin
Author-email: ximena.yeraldin.ll@outlook.es
License: MIT
Keywords: ximyer
Platform: UNKNOWN
Classifier: Development Status :: 3 - Alpha
Classifier: Intended Audience :: Developers
Classifier: Topic :: Software Development :: Build Tools
Classifier: License :: OSI Approved :: MIT License
Classifier: Programming Language :: Python :: 3
License-File: license.txt
